table_maker.py
table_maker-0.1.0.dist-info/LICENSE
table_maker-0.1.0.dist-info/METADATA
table_maker-0.1.0.dist-info/WHEEL
table_maker-0.1.0.dist-info/top_level.txt
table_maker-0.1.0.dist-info/RECORD
