Metadata-Version: 2.1
Name: table-maker
Version: 0.1.0
Summary: Create simple, tastefully-formatted strings that resemble tables
Author-email: "I.R. Whitt" <yvlcmb@protonmail.com>
Project-URL: Homepage, https://gitlab.com/radtbad/table-maker
Project-URL: Bug Reports, https://gitlab.com/ratbad/table-maker/issues
Project-URL: Source, https://gitlab.com/ratbad/table-maker/
Classifier: Programming Language :: Python :: 3
Classifier: License :: OSI Approved :: MIT License
Classifier: Operating System :: OS Independent
Requires-Python: >=3.6
License-File: LICENSE
Provides-Extra: test
Requires-Dist: coverage ; extra == 'test'
Requires-Dist: pytest ; extra == 'test'
